hello_build_agent/__init__.py
hello_build_agent/cli.py
hello_build_agent/loop.py
hello_build_agent/agent/actions.py
hello_build_agent/agent/docker_io.py
hello_build_agent/agent/logger.py
hello_build_agent/agent/qdrant_io.py
hello_build_agent/agent/tracker.py
hello_build_agent-0.5.6.dist-info/METADATA
hello_build_agent-0.5.6.dist-info/WHEEL
hello_build_agent-0.5.6.dist-info/entry_points.txt
hello_build_agent-0.5.6.dist-info/licenses/LICENSE
hello_build_agent-0.5.6.dist-info/RECORD
